wechat_ob12/__init__.py
wechat_ob12-0.0.2.2.dist-info/LICENSE.txt
wechat_ob12-0.0.2.2.dist-info/METADATA
wechat_ob12-0.0.2.2.dist-info/WHEEL
wechat_ob12-0.0.2.2.dist-info/top_level.txt
wechat_ob12-0.0.2.2.dist-info/RECORD
