Metadata-Version: 2.1
Name: wechat_ob12
Version: 0.0.2.2
Summary: onebot12 to wechat
Home-page: https://github.com/Dragon-ts/wechat-ob12
Author: Dragon_ts
Author-email: 2658651085@qq.com
Requires-Python: >=3.6
License-File: LICENSE.txt
